[
  {
    "id": "OGM-Z01-013",
    "beds": 5,
    "finishing": "Semi Finished",
    "areaSqm": 0,
    "priceEGP": 228019000,
    "status": "Available",
    "cluster": "OGM P1",
    "areaNote": "Design: 5BD - 1F",
    "view": "Landscape",
    "deliveryNote": "2027",
    "paymentPlan": "10% down payment over 8 years equal installments"
  },
  {
    "id": "OGM-Z01-016",
    "beds": 5,
    "finishing": "Semi Finished",
    "areaSqm": 0,
    "priceEGP": 221837000,
    "status": "Available",
    "cluster": "OGM P1",
    "areaNote": "Design: 5BD - 1F",
    "view": "Landscape",
    "deliveryNote": "2027",
    "paymentPlan": "10% down payment over 8 years equal installments"
  },
  {
    "id": "OGM-Z01-024",
    "beds": 5,
    "finishing": "Semi Finished",
    "areaSqm": 0,
    "priceEGP": 226783000,
    "status": "Available",
    "cluster": "OGM P1",
    "areaNote": "Design: 5BD - 1F",
    "view": "Landscape",
    "deliveryNote": "2027",
    "paymentPlan": "10% down payment over 8 years equal installments"
  },
  {
    "id": "OGM-Z01-027",
    "beds": 5,
    "finishing": "Semi Finished",
    "areaSqm": 0,
    "priceEGP": 245949000,
    "status": "Available",
    "cluster": "OGM P1",
    "areaNote": "Design: 5BD - 1F",
    "view": "Landscape",
    "deliveryNote": "2027",
    "paymentPlan": "10% down payment over 8 years equal installments"
  },
  {
    "id": "OGM-Z01-030",
    "beds": 5,
    "finishing": "Semi Finished",
    "areaSqm": 0,
    "priceEGP": 227525000,
    "status": "Available",
    "cluster": "OGM P1",
    "areaNote": "Design: 5BD - 1F",
    "view": "Landscape",
    "deliveryNote": "2027",
    "paymentPlan": "10% down payment over 8 years equal installments"
  },
  {
    "id": "OGM-Z01-031",
    "beds": 5,
    "finishing": "Semi Finished",
    "areaSqm": 0,
    "priceEGP": 227525000,
    "status": "Available",
    "cluster": "OGM P1",
    "areaNote": "Design: 5BD - 1F",
    "view": "Landscape",
    "deliveryNote": "2027",
    "paymentPlan": "10% down payment over 8 years equal installments"
  },
  {
    "id": "OGM-Z01-032",
    "beds": 5,
    "finishing": "Semi Finished",
    "areaSqm": 0,
    "priceEGP": 221713000,
    "status": "Available",
    "cluster": "OGM P1",
    "areaNote": "Design: 5BD - 1F",
    "view": "Landscape",
    "deliveryNote": "2027",
    "paymentPlan": "10% down payment over 8 years equal installments"
  },
  {
    "id": "OGM-Z01-034",
    "beds": 5,
    "finishing": "Semi Finished",
    "areaSqm": 0,
    "priceEGP": 231976000,
    "status": "Available",
    "cluster": "OGM P1",
    "areaNote": "Design: 5BD - 1F",
    "view": "Landscape",
    "deliveryNote": "2027",
    "paymentPlan": "10% down payment over 8 years equal installments"
  },
  {
    "id": "OGM-Z01-036",
    "beds": 5,
    "finishing": "Semi Finished",
    "areaSqm": 0,
    "priceEGP": 229503000,
    "status": "Available",
    "cluster": "OGM P1",
    "areaNote": "Design: 5BD - 1F",
    "view": "Landscape",
    "deliveryNote": "2027",
    "paymentPlan": "10% down payment over 8 years equal installments"
  },
  {
    "id": "OGM-Z01-038",
    "beds": 5,
    "finishing": "Semi Finished",
    "areaSqm": 0,
    "priceEGP": 230245000,
    "status": "Available",
    "cluster": "OGM P1",
    "areaNote": "Design: 5BD - 1F",
    "view": "Landscape",
    "deliveryNote": "2027",
    "paymentPlan": "10% down payment over 8 years equal installments"
  },
  {
    "id": "OGM-Z01-039",
    "beds": 5,
    "finishing": "Semi Finished",
    "areaSqm": 0,
    "priceEGP": 226041000,
    "status": "Available",
    "cluster": "OGM P1",
    "areaNote": "Design: 5BD - 1F",
    "view": "Landscape",
    "deliveryNote": "2027",
    "paymentPlan": "10% down payment over 8 years equal installments"
  },
  {
    "id": "OGM-Z01-041",
    "beds": 5,
    "finishing": "Semi Finished",
    "areaSqm": 0,
    "priceEGP": 183134000,
    "status": "Available",
    "cluster": "OGM P1",
    "areaNote": "Design: 4BD - 1F",
    "view": "Landscape",
    "deliveryNote": "2027",
    "paymentPlan": "10% down payment over 8 years equal installments"
  },
  {
    "id": "OGM-Z01-044",
    "beds": 5,
    "finishing": "Semi Finished",
    "areaSqm": 0,
    "priceEGP": 193643000,
    "status": "Available",
    "cluster": "OGM P1",
    "areaNote": "Design: 4BD - 1F",
    "view": "Landscape",
    "deliveryNote": "2027",
    "paymentPlan": "10% down payment over 8 years equal installments"
  },
  {
    "id": "OGM-Z01-052",
    "beds": 5,
    "finishing": "Semi Finished",
    "areaSqm": 0,
    "priceEGP": 180166000,
    "status": "Available",
    "cluster": "OGM P1",
    "areaNote": "Design: 4BD - 1F",
    "view": "Landscape",
    "deliveryNote": "2027",
    "paymentPlan": "10% down payment over 8 years equal installments"
  },
  {
    "id": "OGM-Z01-053",
    "beds": 5,
    "finishing": "Semi Finished",
    "areaSqm": 0,
    "priceEGP": 167182000,
    "status": "Available",
    "cluster": "OGM P1",
    "areaNote": "Design: 4BD - 1F",
    "view": "Landscape",
    "deliveryNote": "2027",
    "paymentPlan": "10% down payment over 8 years equal installments"
  },
  {
    "id": "OGM-Z01-055",
    "beds": 5,
    "finishing": "Semi Finished",
    "areaSqm": 0,
    "priceEGP": 216767000,
    "status": "Available",
    "cluster": "OGM P1",
    "areaNote": "Design: 5BD - 1F",
    "view": "Landscape",
    "deliveryNote": "2027",
    "paymentPlan": "10% down payment over 8 years equal installments"
  },
  {
    "id": "OGM-Z01-056",
    "beds": 5,
    "finishing": "Semi Finished",
    "areaSqm": 0,
    "priceEGP": 212068000,
    "status": "Available",
    "cluster": "OGM P1",
    "areaNote": "Design: 5BD - 1F",
    "view": "Landscape",
    "deliveryNote": "2027",
    "paymentPlan": "10% down payment over 8 years equal installments"
  },
  {
    "id": "OGM-Z01-057",
    "beds": 5,
    "finishing": "Semi Finished",
    "areaSqm": 0,
    "priceEGP": 212562000,
    "status": "Available",
    "cluster": "OGM P1",
    "areaNote": "Design: 5BD - 1F",
    "view": "Landscape",
    "deliveryNote": "2027",
    "paymentPlan": "10% down payment over 8 years equal installments"
  },
  {
    "id": "OGM-Z01-060",
    "beds": 5,
    "finishing": "Semi Finished",
    "areaSqm": 0,
    "priceEGP": 167182000,
    "status": "Available",
    "cluster": "OGM P1",
    "areaNote": "Design: 4BD - 1F",
    "view": "Landscape",
    "deliveryNote": "2027",
    "paymentPlan": "10% down payment over 8 years equal installments"
  },
  {
    "id": "OGM-Z01-061",
    "beds": 5,
    "finishing": "Semi Finished",
    "areaSqm": 0,
    "priceEGP": 166935000,
    "status": "Available",
    "cluster": "OGM P1",
    "areaNote": "Design: 4BD - 1F",
    "view": "Landscape",
    "deliveryNote": "2027",
    "paymentPlan": "10% down payment over 8 years equal installments"
  },
  {
    "id": "OGM-Z02-002",
    "beds": 5,
    "finishing": "Semi Finished",
    "areaSqm": 0,
    "priceEGP": 166935000,
    "status": "Available",
    "cluster": "OGM P1",
    "areaNote": "Design: 4BD - 1F",
    "view": "Landscape",
    "deliveryNote": "2027",
    "paymentPlan": "10% down payment over 8 years equal installments"
  },
  {
    "id": "OGM-Z02-012",
    "beds": 5,
    "finishing": "Semi Finished",
    "areaSqm": 0,
    "priceEGP": 167306000,
    "status": "Available",
    "cluster": "OGM P1",
    "areaNote": "Design: 4BD - 1F",
    "view": "Landscape",
    "deliveryNote": "2027",
    "paymentPlan": "10% down payment over 8 years equal installments"
  },
  {
    "id": "OGM-Z02-015",
    "beds": 5,
    "finishing": "Semi Finished",
    "areaSqm": 0,
    "priceEGP": 226041000,
    "status": "Available",
    "cluster": "OGM P1",
    "areaNote": "Design: 5BD - 1F",
    "view": "Landscape",
    "deliveryNote": "2027",
    "paymentPlan": "10% down payment over 8 years equal installments"
  },
  {
    "id": "OGM-Z02-019",
    "beds": 5,
    "finishing": "Semi Finished",
    "areaSqm": 0,
    "priceEGP": 101645000,
    "status": "Available",
    "cluster": "OGM P1",
    "areaNote": "Design: 4BD - 2F",
    "view": "Landscape",
    "deliveryNote": "2027",
    "paymentPlan": "10% down payment over 8 years equal installments"
  },
  {
    "id": "OGM-Z02-021",
    "beds": 5,
    "finishing": "Semi Finished",
    "areaSqm": 0,
    "priceEGP": 101645000,
    "status": "Available",
    "cluster": "OGM P1",
    "areaNote": "Design: 4BD - 2F",
    "view": "Landscape",
    "deliveryNote": "2027",
    "paymentPlan": "10% down payment over 8 years equal installments"
  },
  {
    "id": "OGM-Z02-027",
    "beds": 5,
    "finishing": "Semi Finished",
    "areaSqm": 0,
    "priceEGP": 84457000,
    "status": "Available",
    "cluster": "OGM P1",
    "areaNote": "Design: 3BD - 2F",
    "view": "Landscape",
    "deliveryNote": "2027",
    "paymentPlan": "10% down payment over 8 years equal installments"
  },
  {
    "id": "OGM-Z02-028",
    "beds": 5,
    "finishing": "Semi Finished",
    "areaSqm": 0,
    "priceEGP": 101645000,
    "status": "Available",
    "cluster": "OGM P1",
    "areaNote": "Design: 4BD - 2F",
    "view": "Landscape",
    "deliveryNote": "2027",
    "paymentPlan": "10% down payment over 8 years equal installments"
  },
  {
    "id": "OGM-Z02-029",
    "beds": 5,
    "finishing": "Semi Finished",
    "areaSqm": 0,
    "priceEGP": 101645000,
    "status": "Available",
    "cluster": "OGM P1",
    "areaNote": "Design: 4BD - 2F",
    "view": "Landscape",
    "deliveryNote": "2027",
    "paymentPlan": "10% down payment over 8 years equal installments"
  },
  {
    "id": "OGM-Z02-030",
    "beds": 5,
    "finishing": "Semi Finished",
    "areaSqm": 0,
    "priceEGP": 84457000,
    "status": "Available",
    "cluster": "OGM P1",
    "areaNote": "Design: 3BD - 2F",
    "view": "Landscape",
    "deliveryNote": "2027",
    "paymentPlan": "10% down payment over 8 years equal installments"
  },
  {
    "id": "OGM-Z02-042",
    "beds": 5,
    "finishing": "Semi Finished",
    "areaSqm": 0,
    "priceEGP": 76543000,
    "status": "Available",
    "cluster": "OGM P1",
    "areaNote": "Design: 4BD - 2F",
    "view": "Landscape",
    "deliveryNote": "2027",
    "paymentPlan": "10% down payment over 8 years equal installments"
  },
  {
    "id": "OGM-Z02-048",
    "beds": 5,
    "finishing": "Semi Finished",
    "areaSqm": 0,
    "priceEGP": 76048000,
    "status": "Available",
    "cluster": "OGM P1",
    "areaNote": "Design: 4BD - 2F",
    "view": "Landscape",
    "deliveryNote": "2027",
    "paymentPlan": "10% down payment over 8 years equal installments"
  },
  {
    "id": "OGM-Z02-054",
    "beds": 5,
    "finishing": "Semi Finished",
    "areaSqm": 0,
    "priceEGP": 63065000,
    "status": "Available",
    "cluster": "OGM P1",
    "areaNote": "Design: 3BD - 2F",
    "view": "Landscape",
    "deliveryNote": "2027",
    "paymentPlan": "10% down payment over 8 years equal installments"
  },
  {
    "id": "OGM-Z02-056",
    "beds": 5,
    "finishing": "Semi Finished",
    "areaSqm": 0,
    "priceEGP": 76048000,
    "status": "Available",
    "cluster": "OGM P1",
    "areaNote": "Design: 4BD - 2F",
    "view": "Landscape",
    "deliveryNote": "2027",
    "paymentPlan": "10% down payment over 8 years equal installments"
  },
  {
    "id": "OGM-Z02-057",
    "beds": 5,
    "finishing": "Semi Finished",
    "areaSqm": 0,
    "priceEGP": 76048000,
    "status": "Available",
    "cluster": "OGM P1",
    "areaNote": "Design: 4BD - 2F",
    "view": "Landscape",
    "deliveryNote": "2027",
    "paymentPlan": "10% down payment over 8 years equal installments"
  },
  {
    "id": "OGM-Z02-058",
    "beds": 5,
    "finishing": "Semi Finished",
    "areaSqm": 0,
    "priceEGP": 75925000,
    "status": "Available",
    "cluster": "OGM P1",
    "areaNote": "Design: 4BD - 2F",
    "view": "Landscape",
    "deliveryNote": "2027",
    "paymentPlan": "10% down payment over 8 years equal installments"
  },
  {
    "id": "OGM-Z02-059",
    "beds": 5,
    "finishing": "Semi Finished",
    "areaSqm": 0,
    "priceEGP": 63436000,
    "status": "Available",
    "cluster": "OGM P1",
    "areaNote": "Design: 3BD - 2F",
    "view": "Landscape",
    "deliveryNote": "2027",
    "paymentPlan": "10% down payment over 8 years equal installments"
  },
  {
    "id": "OGM-Z02-062",
    "beds": 5,
    "finishing": "Semi Finished",
    "areaSqm": 0,
    "priceEGP": 80129000,
    "status": "Available",
    "cluster": "OGM P1",
    "areaNote": "Design: 3BD - 2F",
    "view": "Landscape",
    "deliveryNote": "2027",
    "paymentPlan": "10% down payment over 8 years equal installments"
  },
  {
    "id": "OGM-Z02-065",
    "beds": 5,
    "finishing": "Semi Finished",
    "areaSqm": 0,
    "priceEGP": 86064000,
    "status": "Available",
    "cluster": "OGM P1",
    "areaNote": "Design: 4BD - 2F",
    "view": "Landscape",
    "deliveryNote": "2027",
    "paymentPlan": "10% down payment over 8 years equal installments"
  },
  {
    "id": "OGM-Z02-067",
    "beds": 5,
    "finishing": "Semi Finished",
    "areaSqm": 0,
    "priceEGP": 86188000,
    "status": "Available",
    "cluster": "OGM P1",
    "areaNote": "Design: 4BD - 2F",
    "view": "Landscape",
    "deliveryNote": "2027",
    "paymentPlan": "10% down payment over 8 years equal installments"
  },
  {
    "id": "OGM-Z02-068",
    "beds": 5,
    "finishing": "Semi Finished",
    "areaSqm": 0,
    "priceEGP": 71597000,
    "status": "Available",
    "cluster": "OGM P1",
    "areaNote": "Design: 3BD - 2F",
    "view": "Landscape",
    "deliveryNote": "2027",
    "paymentPlan": "10% down payment over 8 years equal installments"
  },
  {
    "id": "OGM-Z02-069",
    "beds": 5,
    "finishing": "Semi Finished",
    "areaSqm": 0,
    "priceEGP": 71597000,
    "status": "Available",
    "cluster": "OGM P1",
    "areaNote": "Design: 3BD - 2F",
    "view": "Landscape",
    "deliveryNote": "2027",
    "paymentPlan": "10% down payment over 8 years equal installments"
  },
  {
    "id": "OGM-Z02-080",
    "beds": 5,
    "finishing": "Semi Finished",
    "areaSqm": 0,
    "priceEGP": 86188000,
    "status": "Available",
    "cluster": "OGM P1",
    "areaNote": "Design: 4BD - 2F",
    "view": "Landscape",
    "deliveryNote": "2027",
    "paymentPlan": "10% down payment over 8 years equal installments"
  },
  {
    "id": "OGM-Z02-081",
    "beds": 5,
    "finishing": "Semi Finished",
    "areaSqm": 0,
    "priceEGP": 71597000,
    "status": "Available",
    "cluster": "OGM P1",
    "areaNote": "Design: 3BD - 2F",
    "view": "Landscape",
    "deliveryNote": "2027",
    "paymentPlan": "10% down payment over 8 years equal installments"
  },
  {
    "id": "OGM-Z02-099",
    "beds": 5,
    "finishing": "Semi Finished",
    "areaSqm": 0,
    "priceEGP": 68629000,
    "status": "Available",
    "cluster": "OGM P1",
    "areaNote": "Design: 3BD - 2F",
    "view": "Landscape",
    "deliveryNote": "2027",
    "paymentPlan": "10% down payment over 8 years equal installments"
  },
  {
    "id": "OGM-Z02-100",
    "beds": 5,
    "finishing": "Semi Finished",
    "areaSqm": 0,
    "priceEGP": 82602000,
    "status": "Available",
    "cluster": "OGM P1",
    "areaNote": "Design: 4BD - 2F",
    "view": "Landscape",
    "deliveryNote": "2027",
    "paymentPlan": "10% down payment over 8 years equal installments"
  },
  {
    "id": "OGM-Z02-102",
    "beds": 5,
    "finishing": "Semi Finished",
    "areaSqm": 0,
    "priceEGP": 82602000,
    "status": "Available",
    "cluster": "OGM P1",
    "areaNote": "Design: 4BD - 2F",
    "view": "Landscape",
    "deliveryNote": "2027",
    "paymentPlan": "10% down payment over 8 years equal installments"
  },
  {
    "id": "OGM-Z02-103",
    "beds": 5,
    "finishing": "Semi Finished",
    "areaSqm": 0,
    "priceEGP": 74564000,
    "status": "Available",
    "cluster": "OGM P1",
    "areaNote": "Design: 3BD - 2F",
    "view": "Landscape",
    "deliveryNote": "2027",
    "paymentPlan": "10% down payment over 8 years equal installments"
  },
  {
    "id": "OGM-Z02-105",
    "beds": 5,
    "finishing": "Semi Finished",
    "areaSqm": 0,
    "priceEGP": 74688000,
    "status": "Available",
    "cluster": "OGM P1",
    "areaNote": "Design: 3BD - 2F",
    "view": "Landscape",
    "deliveryNote": "2027",
    "paymentPlan": "10% down payment over 8 years equal installments"
  },
  {
    "id": "OGM-Z02-106",
    "beds": 5,
    "finishing": "Semi Finished",
    "areaSqm": 0,
    "priceEGP": 77161000,
    "status": "Available",
    "cluster": "OGM P1",
    "areaNote": "Design: 3BD - 2F",
    "view": "Landscape",
    "deliveryNote": "2027",
    "paymentPlan": "10% down payment over 8 years equal installments"
  },
  {
    "id": "OGM-Z02-115",
    "beds": 5,
    "finishing": "Semi Finished",
    "areaSqm": 0,
    "priceEGP": 96204000,
    "status": "Available",
    "cluster": "OGM P1",
    "areaNote": "Design: 4BD - 2F",
    "view": "Landscape",
    "deliveryNote": "2027",
    "paymentPlan": "10% down payment over 8 years equal installments"
  },
  {
    "id": "OGM-Z04-007",
    "beds": 5,
    "finishing": "Semi Finished",
    "areaSqm": 0,
    "priceEGP": 76543000,
    "status": "Available",
    "cluster": "OGM P1",
    "areaNote": "Design: 4BD - 2F",
    "view": "Landscape",
    "deliveryNote": "2027",
    "paymentPlan": "10% down payment over 8 years equal installments"
  },
  {
    "id": "OGM-Z04-009",
    "beds": 5,
    "finishing": "Semi Finished",
    "areaSqm": 0,
    "priceEGP": 62446000,
    "status": "Available",
    "cluster": "OGM P1",
    "areaNote": "Design: 3BD - 2F",
    "view": "Landscape",
    "deliveryNote": "2027",
    "paymentPlan": "10% down payment over 8 years equal installments"
  },
  {
    "id": "OGM-Z04-014",
    "beds": 5,
    "finishing": "Semi Finished",
    "areaSqm": 0,
    "priceEGP": 62446000,
    "status": "Available",
    "cluster": "OGM P1",
    "areaNote": "Design: 3BD - 2F",
    "view": "Landscape",
    "deliveryNote": "2027",
    "paymentPlan": "10% down payment over 8 years equal installments"
  },
  {
    "id": "OGM-Z04-016",
    "beds": 5,
    "finishing": "Semi Finished",
    "areaSqm": 0,
    "priceEGP": 75059000,
    "status": "Available",
    "cluster": "OGM P1",
    "areaNote": "Design: 4BD - 2F",
    "view": "Landscape",
    "deliveryNote": "2027",
    "paymentPlan": "10% down payment over 8 years equal installments"
  },
  {
    "id": "OGM-Z04-033",
    "beds": 5,
    "finishing": "Semi Finished",
    "areaSqm": 0,
    "priceEGP": 75183000,
    "status": "Available",
    "cluster": "OGM P1",
    "areaNote": "Design: 4BD - 2F",
    "view": "Landscape",
    "deliveryNote": "2027",
    "paymentPlan": "10% down payment over 8 years equal installments"
  },
  {
    "id": "OGM-Z04-037",
    "beds": 5,
    "finishing": "Semi Finished",
    "areaSqm": 0,
    "priceEGP": 77285000,
    "status": "Available",
    "cluster": "OGM P1",
    "areaNote": "Design: 4BD - 2F",
    "view": "Landscape",
    "deliveryNote": "2027",
    "paymentPlan": "10% down payment over 8 years equal installments"
  },
  {
    "id": "OGM-Z04-039",
    "beds": 5,
    "finishing": "Semi Finished",
    "areaSqm": 0,
    "priceEGP": 75554000,
    "status": "Available",
    "cluster": "OGM P1",
    "areaNote": "Design: 4BD - 2F",
    "view": "Landscape",
    "deliveryNote": "2027",
    "paymentPlan": "10% down payment over 8 years equal installments"
  },
  {
    "id": "OGM-Z05-031",
    "beds": 5,
    "finishing": "Semi Finished",
    "areaSqm": 0,
    "priceEGP": 69247000,
    "status": "Available",
    "cluster": "OGM P1",
    "areaNote": "Design: 3BD - 2F",
    "view": "Landscape",
    "deliveryNote": "2027",
    "paymentPlan": "10% down payment over 8 years equal installments"
  },
  {
    "id": "OGM-Z05-049",
    "beds": 5,
    "finishing": "Semi Finished",
    "areaSqm": 0,
    "priceEGP": 75306000,
    "status": "Available",
    "cluster": "OGM P1",
    "areaNote": "Design: 4BD - 2F",
    "view": "Landscape",
    "deliveryNote": "2027",
    "paymentPlan": "10% down payment over 8 years equal installments"
  },
  {
    "id": "OGM-Z05-151",
    "beds": 5,
    "finishing": "Semi Finished",
    "areaSqm": 0,
    "priceEGP": 67640000,
    "status": "Available",
    "cluster": "OGM P1",
    "areaNote": "Design: 3BD - 2F",
    "view": "Landscape",
    "deliveryNote": "2027",
    "paymentPlan": "10% down payment over 8 years equal installments"
  },
  {
    "id": "OGM-Z05-152",
    "beds": 5,
    "finishing": "Semi Finished",
    "areaSqm": 0,
    "priceEGP": 63683000,
    "status": "Available",
    "cluster": "OGM P1",
    "areaNote": "Design: 3BD - 2F",
    "view": "Landscape",
    "deliveryNote": "2027",
    "paymentPlan": "10% down payment over 8 years equal installments"
  },
  {
    "id": "OGM-Z05-155",
    "beds": 5,
    "finishing": "Semi Finished",
    "areaSqm": 0,
    "priceEGP": 63312000,
    "status": "Available",
    "cluster": "OGM P1",
    "areaNote": "Design: 3BD - 2F",
    "view": "Landscape",
    "deliveryNote": "2027",
    "paymentPlan": "10% down payment over 8 years equal installments"
  },
  {
    "id": "OGM-Z05-156",
    "beds": 5,
    "finishing": "Semi Finished",
    "areaSqm": 0,
    "priceEGP": 64301000,
    "status": "Available",
    "cluster": "OGM P1",
    "areaNote": "Design: 3BD - 2F",
    "view": "Landscape",
    "deliveryNote": "2027",
    "paymentPlan": "10% down payment over 8 years equal installments"
  },
  {
    "id": "OGM-Z05-157",
    "beds": 5,
    "finishing": "Semi Finished",
    "areaSqm": 0,
    "priceEGP": 66156000,
    "status": "Available",
    "cluster": "OGM P1",
    "areaNote": "Design: 3BD - 2F",
    "view": "Landscape",
    "deliveryNote": "2027",
    "paymentPlan": "10% down payment over 8 years equal installments"
  },
  {
    "id": "OGM-Z06-039",
    "beds": 5,
    "finishing": "Semi Finished",
    "areaSqm": 0,
    "priceEGP": 56016000,
    "status": "Available",
    "cluster": "OGM P1",
    "areaNote": "Design: 3BD - 2F",
    "view": "Landscape",
    "deliveryNote": "2027",
    "paymentPlan": "10% down payment over 8 years equal installments"
  }
]